poetry_pyinvoke_plugin/plugin.py
poetry_pyinvoke_plugin-0.5.0.dist-info/LICENSE
poetry_pyinvoke_plugin-0.5.0.dist-info/METADATA
poetry_pyinvoke_plugin-0.5.0.dist-info/WHEEL
poetry_pyinvoke_plugin-0.5.0.dist-info/entry_points.txt
poetry_pyinvoke_plugin-0.5.0.dist-info/RECORD
