Metadata-Version: 2.1
Name: poetry-pyinvoke-plugin
Version: 0.5.0
Summary: A plugin for poetry that allows you to execute scripts defined in your tasks.py using pyinvoke. Inspired by poetry-exec-plugin.
Home-page: https://github.com/neozenith/poetry-pyinvoke-plugin
License: MIT
Author: neozenith
Requires-Python: >=3.8.1,<4
Classifier: License :: OSI Approved :: MIT License
Classifier: Programming Language :: Python :: 3
Classifier: Programming Language :: Python :: 3.9
Classifier: Programming Language :: Python :: 3.10
Classifier: Programming Language :: Python :: 3.11
Classifier: Programming Language :: Python :: 3.12
Requires-Dist: invoke (>=2.2.0,<3.0.0)
Requires-Dist: poetry (>=1.6.1,<2.0.0)
Requires-Dist: simple-chalk (>=0.1.0,<0.2.0)
Requires-Dist: toml (>=0.10.2,<0.11.0)
Project-URL: Repository, https://github.com/neozenith/poetry-pyinvoke-plugin
